mcp_server_fetch/__init__.py
mcp_server_fetch/cli.py
mcp_server_fetch/server.py
mcp_fetch_server-0.1.9.dist-info/METADATA
mcp_fetch_server-0.1.9.dist-info/WHEEL
mcp_fetch_server-0.1.9.dist-info/entry_points.txt
mcp_fetch_server-0.1.9.dist-info/top_level.txt
mcp_fetch_server-0.1.9.dist-info/RECORD
