Metadata-Version: 2.4
Name: mcp_fetch_server
Version: 0.1.9
Summary: MCP Server for fetching web content
Author-email: MCP Developer <example@example.com>
Requires-Python: >=3.7
Requires-Dist: requests
Requires-Dist: beautifulsoup4
Requires-Dist: click
Requires-Dist: uvicorn
Requires-Dist: fastapi
Provides-Extra: mcp
Requires-Dist: mcp; extra == "mcp"
